brainpy/__init__.py
brainpy/_add_deprecations.py
brainpy/analysis.py
brainpy/channels.py
brainpy/check.py
brainpy/checkpoints.py
brainpy/connect.py
brainpy/encoding.py
brainpy/errors.py
brainpy/experimental.py
brainpy/initialize.py
brainpy/inputs.py
brainpy/layers.py
brainpy/losses.py
brainpy/measure.py
brainpy/mixin.py
brainpy/neurons.py
brainpy/optim.py
brainpy/rates.py
brainpy/running.py
brainpy/synapses.py
brainpy/synouts.py
brainpy/synplast.py
brainpy/tools.py
brainpy/types.py
brainpy/_src/__init__.py
brainpy/_src/_delay.py
brainpy/_src/checking.py
brainpy/_src/context.py
brainpy/_src/delay.py
brainpy/_src/dependency_check.py
brainpy/_src/deprecations.py
brainpy/_src/dynsys.py
brainpy/_src/helpers.py
brainpy/_src/mixin.py
brainpy/_src/modes.py
brainpy/_src/runners.py
brainpy/_src/transform.py
brainpy/_src/types.py
brainpy/_src/analysis/__init__.py
brainpy/_src/analysis/base.py
brainpy/_src/analysis/constants.py
brainpy/_src/analysis/plotstyle.py
brainpy/_src/analysis/stability.py
brainpy/_src/analysis/highdim/__init__.py
brainpy/_src/analysis/highdim/slow_points.py
brainpy/_src/analysis/lowdim/__init__.py
brainpy/_src/analysis/lowdim/lowdim_analyzer.py
brainpy/_src/analysis/lowdim/lowdim_bifurcation.py
brainpy/_src/analysis/lowdim/lowdim_phase_plane.py
brainpy/_src/analysis/utils/__init__.py
brainpy/_src/analysis/utils/function.py
brainpy/_src/analysis/utils/measurement.py
brainpy/_src/analysis/utils/model.py
brainpy/_src/analysis/utils/optimization.py
brainpy/_src/analysis/utils/others.py
brainpy/_src/analysis/utils/outputs.py
brainpy/_src/analysis/utils/visualization.py
brainpy/_src/checkpoints/__init__.py
brainpy/_src/checkpoints/serialization.py
brainpy/_src/connect/__init__.py
brainpy/_src/connect/base.py
brainpy/_src/connect/custom_conn.py
brainpy/_src/connect/random_conn.py
brainpy/_src/connect/regular_conn.py
brainpy/_src/dnn/__init__.py
brainpy/_src/dnn/activations.py
brainpy/_src/dnn/base.py
brainpy/_src/dnn/conv.py
brainpy/_src/dnn/dropout.py
brainos-2.5.0.post20240308.dist-info/LICENSE
brainos-2.5.0.post20240308.dist-info/METADATA
brainos-2.5.0.post20240308.dist-info/WHEEL
brainos-2.5.0.post20240308.dist-info/dependency_links.txt
brainos-2.5.0.post20240308.dist-info/top_level.txt
brainos-2.5.0.post20240308.dist-info/RECORD
