Metadata-Version: 2.1
Name: brainos
Version: 2.5.0.post20240308
Summary: BrainPy: Brain Dynamics Programming in Python
Home-page: https://github.com/brainpy/BrainPy
Author: BrainPy Team
Author-email: chao.brain@qq.com
License: GPL-3.0 license
Project-URL: Bug Tracker, https://github.com/brainpy/BrainPy/issues
Project-URL: Documentation, https://brainpy.readthedocs.io/
Project-URL: Source Code, https://github.com/brainpy/BrainPy
Keywords: computational neuroscience,brain-inspired computation,brain modeling,brain dynamics modeling,brain dynamics programming
Classifier: Natural Language :: English
Classifier: Operating System :: OS Independent
Classifier: Programming Language :: Python
Classifier: Programming Language :: Python :: 3
Classifier: Programming Language :: Python :: 3.9
Classifier: Programming Language :: Python :: 3.10
Classifier: Programming Language :: Python :: 3.11
Classifier: Programming Language :: Python :: 3.12
Classifier: Intended Audience :: Science/Research
Classifier: License :: OSI Approved :: Apache Software License
Classifier: Topic :: Scientific/Engineering :: Bio-Informatics
Classifier: Topic :: Scientific/Engineering :: Mathematics
Classifier: Topic :: Scientific/Engineering :: Artificial Intelligence
Classifier: Topic :: Software Development :: Libraries
Requires-Python: >=3.9
License-File: LICENSE
Requires-Dist: numpy (>=1.15)
Requires-Dist: jax (>=0.4.13)
Requires-Dist: tqdm
Provides-Extra: cpu
Requires-Dist: jaxlib (>=0.4.13) ; extra == 'cpu'
Requires-Dist: brainpylib ; extra == 'cpu'
Requires-Dist: numba ; extra == 'cpu'
Requires-Dist: taichi (==1.7.0) ; extra == 'cpu'
Provides-Extra: cpu_mini
Requires-Dist: jaxlib (>=0.4.13) ; extra == 'cpu_mini'
Provides-Extra: cuda11
Requires-Dist: jaxlib[cuda11_pip] ; extra == 'cuda11'
Requires-Dist: brainpylib ; extra == 'cuda11'
Requires-Dist: numba ; extra == 'cuda11'
Requires-Dist: taichi (==1.7.0) ; extra == 'cuda11'
Provides-Extra: cuda11_mini
Requires-Dist: jaxlib[cuda11_pip] ; extra == 'cuda11_mini'
Provides-Extra: cuda12
Requires-Dist: jaxlib[cuda12_pip] ; extra == 'cuda12'
Requires-Dist: brainpylib ; extra == 'cuda12'
Requires-Dist: numba ; extra == 'cuda12'
Requires-Dist: taichi (==1.7.0) ; extra == 'cuda12'
Provides-Extra: cuda12_mini
Requires-Dist: jaxlib[cuda12_pip] ; extra == 'cuda12_mini'
Provides-Extra: tpu
Requires-Dist: jaxlib[tpu] ; extra == 'tpu'
Requires-Dist: numba ; extra == 'tpu'
